tigerasi/__init__.py
tigerasi/device_codes.py
tigerasi/sim_tiger_controller.py
tigerasi/tiger_controller.py
tigerasi-0.0.27.dist-info/LICENSE
tigerasi-0.0.27.dist-info/METADATA
tigerasi-0.0.27.dist-info/WHEEL
tigerasi-0.0.27.dist-info/top_level.txt
tigerasi-0.0.27.dist-info/RECORD
