Metadata-Version: 2.2
Name: tigerasi
Version: 0.0.27
Summary: a lightweight python driver for ASI brand Tiger Controllers
Author-email: Joshua Vasquez <joshua.vasquez@alleninstitute.org>, Adam Glaser <adam.glaser@alleninstitute.org>
License: MIT
Project-URL: repository, https://github.com/AllenNeuralDynamics/TigerASI
Keywords: microscopy,tiger,asi
Classifier: License :: OSI Approved :: MIT License
Classifier: Development Status :: 4 - Beta
Classifier: Programming Language :: Python
Requires-Python: >=3.9
License-File: LICENSE
Requires-Dist: pyserial
Provides-Extra: dev
Requires-Dist: sphinx; extra == "dev"
Requires-Dist: furo; extra == "dev"
Requires-Dist: enum-tools[sphinx]; extra == "dev"
